.gitignore
.readthedocs.yml
.travis.yml
CHANGELOG.rst
LICENSE
MANIFEST.in
README.rst
setup.cfg
setup.py
tox.ini
docs/Makefile
docs/conf.py
docs/index.rst
docs/installation.rst
docs/_static/custom.css
docs/_static/favicon.ico
docs/_static/logo.png
docs/_static/logo_packed.png
docs/_templates/about.html
docs/api/index.rst
docs/usage/standalone.rst
docs/usage/tendril.rst
src/tendril/__init__.py
src/tendril/utils/__init__.py
src/tendril/utils/parsers/__init__.py
src/tendril/utils/parsers/media/__init__.py
src/tendril/utils/parsers/media/av.py
src/tendril/utils/parsers/media/base.py
src/tendril/utils/parsers/media/documents.py
src/tendril/utils/parsers/media/images.py
src/tendril/utils/parsers/media/info.py
src/tendril/utils/parsers/media/thumbnails.py
src/tendril/utils/parsers/media/videos.py
src/tendril_utils_media.egg-info/PKG-INFO
src/tendril_utils_media.egg-info/SOURCES.txt
src/tendril_utils_media.egg-info/dependency_links.txt
src/tendril_utils_media.egg-info/requires.txt
src/tendril_utils_media.egg-info/top_level.txt